setup.cfg
setup.py
Flask_Less.egg-info/PKG-INFO
Flask_Less.egg-info/SOURCES.txt
Flask_Less.egg-info/dependency_links.txt
Flask_Less.egg-info/not-zip-safe
Flask_Less.egg-info/requires.txt
Flask_Less.egg-info/top_level.txt
flask_less/__init__.py